LICENSE
MANIFEST.in
README.md
setup.cfg
setup.py
tw2/__init__.py
tw2.jqplugins.select2.egg-info/PKG-INFO
tw2.jqplugins.select2.egg-info/SOURCES.txt
tw2.jqplugins.select2.egg-info/dependency_links.txt
tw2.jqplugins.select2.egg-info/entry_points.txt
tw2.jqplugins.select2.egg-info/namespace_packages.txt
tw2.jqplugins.select2.egg-info/not-zip-safe
tw2.jqplugins.select2.egg-info/requires.txt
tw2.jqplugins.select2.egg-info/top_level.txt
tw2/jqplugins/__init__.py
tw2/jqplugins/select2/__init__.py
tw2/jqplugins/select2/samples.py
tw2/jqplugins/select2/widgets.py
tw2/jqplugins/select2/static/LICENSE
tw2/jqplugins/select2/static/README.md
tw2/jqplugins/select2/static/component.json
tw2/jqplugins/select2/static/select2-spinner.gif
tw2/jqplugins/select2/static/select2.css
tw2/jqplugins/select2/static/select2.jquery.json
tw2/jqplugins/select2/static/select2.js
tw2/jqplugins/select2/static/select2.min.js
tw2/jqplugins/select2/static/select2.png
tw2/jqplugins/select2/static/select2_locale_es.js
tw2/jqplugins/select2/static/select2_locale_hu.js
tw2/jqplugins/select2/static/select2_locale_it.js
tw2/jqplugins/select2/static/select2x2.png