Metadata-Version: 1.1
Name: tw2.jqplugins.select2
Version: 0.1.6
Summary: ToscaWidgets 2 SelectFields enhanced with the select2 javascript library.
Home-page: https://github.com/toscawidgets/tw2.jqplugins.select2
Author: Ralph Bean
Author-email: rbean@redhat.com
License: MIT
Keywords: toscawidgets.widgets
Platform: UNKNOWN
Classifier: Development Status :: 3 - Alpha
Classifier: Environment :: Web Environment
Classifier: Environment :: Web Environment :: ToscaWidgets
Classifier: Topic :: Software Development :: Libraries :: Python Modules
Classifier: Topic :: Software Development :: Widget Sets
Classifier: Intended Audience :: Developers
Classifier: Operating System :: OS Independent
Classifier: Programming Language :: Python
